brazil_fields/__init__.py
brazil_fields/fields.py
brazil_fields/models.py
brazil_fields/tests.py
django_brazil_fields-0.0.3.dist-info/top_level.txt
django_brazil_fields-0.0.3.dist-info/METADATA
django_brazil_fields-0.0.3.dist-info/DESCRIPTION.rst
django_brazil_fields-0.0.3.dist-info/metadata.json
django_brazil_fields-0.0.3.dist-info/WHEEL
django_brazil_fields-0.0.3.dist-info/RECORD
