Metadata-Version: 2.0
Name: django-brazil-fields
Version: 0.0.3
Summary: Biblioteca com os campos para os tipos de dados usados no Brasil.
Home-page: https://github.com/gestaolivre/django-brazil-fields
Author: Gestão Livre
Author-email: contato@gestaolivre.org
License: MIT
Download-URL: https://github.com/gestaolivre/django-brazil-fields/releases
Keywords: django fields brazil types receita federal
Platform: UNKNOWN
Classifier: Development Status :: 3 - Alpha
Classifier: Environment :: Web Environment
Classifier: Intended Audience :: Developers
Classifier: Operating System :: OS Independent
Classifier: License :: OSI Approved :: MIT License
Classifier: Programming Language :: Python :: 2
Classifier: Programming Language :: Python :: 2.7
Classifier: Programming Language :: Python :: 3
Classifier: Programming Language :: Python :: 3.4
Classifier: Programming Language :: Python :: 3.5
Classifier: Framework :: Django
Requires-Dist: Django (>=1.8)
Requires-Dist: brazil-types
